jupyterquiz/__init__.py
jupyterquiz/styles.css
jupyterquiz/dynamic/__init__.py
jupyterquiz/dynamic/capture.py
jupyterquiz/dynamic/display.py
jupyterquiz/dynamic/loader.py
jupyterquiz/dynamic/renderer.py
jupyterquiz/js/async_suffix.js.tpl
jupyterquiz/js/helpers.js
jupyterquiz/js/multiple_choice.js
jupyterquiz/js/numeric.js
jupyterquiz/js/show_questions.js
jupyterquiz/js/static_suffix.js.tpl
jupyterquiz/js/string.js
jupyterquiz-2.9.6.2.dist-info/LICENSE
jupyterquiz-2.9.6.2.dist-info/WHEEL
jupyterquiz-2.9.6.2.dist-info/METADATA
jupyterquiz-2.9.6.2.dist-info/RECORD
