Metadata-Version: 2.1
Name: JupyterQuiz
Version: 2.9.6.2
Summary: Interactive quizzes for Jupyter and Jupyter Book
Author-email: "John M. Shea" <jshea@ieee.org>
Classifier: License :: OSI Approved :: MIT License
Project-URL: home-page, https://github.com/jmshea/jupyterquiz
